{
  "sections": {
    "rich_text_DWUf4Y": {
      "type": "rich-text",
      "blocks": {
        "heading_RhBiym": {
          "type": "heading",
          "settings": { "heading": "OM DUMBPHONE", "heading_size": "h1" }
        },
        "text_mLREkW": {
          "type": "text",
          "settings": {
            "text": "<p>Hej og hjerteligt velkommen til shop-Dumbphone.dk. Hos Dumbphone har vi  nu udvidet forretningen, således at vi kan gøre det nemmere for familier, venner, roomies eller hele klasse at få fingre i deres helt egen Dumbphone.<\/p>"
          }
        },
        "button_7zMTqL": {
          "type": "button",
          "settings": {
            "button_label": "Shop Dumbphones her!",
            "button_link": "shopify:\/\/collections\/vores-dumbphones",
            "button_style_secondary": false,
            "button_label_2": "",
            "button_link_2": "",
            "button_style_secondary_2": false
          }
        }
      },
      "block_order": ["heading_RhBiym", "text_mLREkW", "button_7zMTqL"],
      "settings": {
        "desktop_content_position": "center",
        "content_alignment": "center",
        "color_scheme": "",
        "full_width": true,
        "padding_top": 40,
        "padding_bottom": 52
      }
    },
    "image_with_text_tU3CRX": {
      "type": "image-with-text",
      "blocks": {
        "heading_WmVPE4": {
          "type": "heading",
          "settings": { "heading": "Hvem står bag?", "heading_size": "h2" }
        },
        "text_76DiUq": {
          "type": "text",
          "settings": {
            "text": "<p>Mit navn er Arne, jeg er 31 år og færdiguddannet som Kaospilot. Jeg bor i Aarhus med min hund Tikko og er den stolte stifter af <strong>Dumbphone-projektet.<\/strong><br\/><br\/>Min rejse mod en mere simpel tilværelse begyndte for 3 år siden, da min smartphone gik i stykker, og jeg nødtvungent skiftede til en Dumbphone.<\/p><p>...Dette skifte viste sig at skulle forvandle mit liv - jeg følte mig mere til stede, havde mere overskud, og oplevede mindre stress og angst, hvilket også førte til bedre søvn.<\/p>",
            "text_style": "body"
          }
        },
        "button_Rxnfmg": {
          "type": "button",
          "settings": {
            "button_label": "",
            "button_link": "",
            "button_style_secondary": false
          }
        }
      },
      "block_order": ["heading_WmVPE4", "text_76DiUq", "button_Rxnfmg"],
      "settings": {
        "image": "shopify:\/\/shop_images\/Om_os_85c1a95c-b52e-4cf0-8f06-532eada8e7ab.png",
        "height": "adapt",
        "desktop_image_width": "medium",
        "layout": "image_first",
        "image_behavior": "none",
        "content_layout": "no-overlap",
        "desktop_content_position": "middle",
        "desktop_content_alignment": "left",
        "mobile_content_alignment": "left",
        "section_color_scheme": "",
        "color_scheme": "",
        "padding_top": 36,
        "padding_bottom": 0
      }
    },
    "image_with_text_xQcGLD": {
      "type": "image-with-text",
      "blocks": {
        "heading_mcLMqV": {
          "type": "heading",
          "settings": { "heading": "", "heading_size": "h1" }
        },
        "text_QFaVKN": {
          "type": "text",
          "settings": {
            "text": "<p>Det var lige her at idéen til Dumbphone opstod. Jeg opdagede nemlig, at mange andre havde delt lignende positive oplevelser online, men hvad kunne man gøre ved det?<\/p><p>Det slog mig, at skiftet til en simplere telefon måske kunne hjælpe mange med de udfordringer, der er så udbredte i dag, heriblandt angst, stress og depression.<\/p><p>Min ambition med Dumbphone.dk er at gøre skiftet til en dumbphone så let og tiltalende som muligt, særligt for at bekæmpe frygten for isolation og det at gå glip af noget (FOMO).<\/p>",
            "text_style": "body"
          }
        },
        "button_Eh8hdT": {
          "type": "button",
          "settings": {
            "button_label": "Se vores udvalg",
            "button_link": "shopify:\/\/collections",
            "button_style_secondary": false
          }
        }
      },
      "block_order": ["heading_mcLMqV", "text_QFaVKN", "button_Eh8hdT"],
      "settings": {
        "image": "shopify:\/\/shop_images\/Om_os_2_af384e33-725b-4790-8672-d5fa72922f16.png",
        "height": "adapt",
        "desktop_image_width": "medium",
        "layout": "text_first",
        "image_behavior": "none",
        "content_layout": "no-overlap",
        "desktop_content_position": "middle",
        "desktop_content_alignment": "left",
        "mobile_content_alignment": "left",
        "section_color_scheme": "",
        "color_scheme": "",
        "padding_top": 0,
        "padding_bottom": 36
      }
    },
    "image_banner_V9TRwP": {
      "type": "image-banner",
      "blocks": {
        "heading_L7zMWr": {
          "type": "heading",
          "settings": { "heading": "", "heading_size": "h1" }
        },
        "text_MVbffh": {
          "type": "text",
          "settings": { "text": "", "text_style": "body" }
        },
        "buttons_6BDADY": {
          "type": "buttons",
          "settings": {
            "button_label_1": "",
            "button_link_1": "",
            "button_style_secondary_1": false,
            "button_label_2": "",
            "button_link_2": "",
            "button_style_secondary_2": false
          }
        }
      },
      "block_order": ["heading_L7zMWr", "text_MVbffh", "buttons_6BDADY"],
      "settings": {
        "image": "shopify:\/\/shop_images\/Banner_783216c2-3168-4693-aa9f-ef4d89284cf7.png",
        "image_overlay_opacity": 0,
        "image_height": "medium",
        "image_behavior": "none",
        "desktop_content_position": "middle-center",
        "desktop_content_alignment": "center",
        "show_text_box": false,
        "color_scheme": "",
        "stack_images_on_mobile": true,
        "mobile_content_alignment": "center",
        "show_text_below": true
      }
    },
    "image_with_text_M9M7XT": {
      "type": "image-with-text",
      "blocks": {
        "heading_4NpeXJ": {
          "type": "heading",
          "settings": { "heading": "", "heading_size": "h1" }
        },
        "text_9hfWtU": {
          "type": "text",
          "settings": {
            "text": "<p>Med det formål at sprede budskabet bredere og gøre Dumbphone mere tilgængelig for alle, besluttede jeg at starte denne webshop. Denne platform giver folk fra hele landet mulighed for at udforske og købe deres egen Dumbphone samt nøje udvalgt tilbehør, der understøtter en sundere, mere bevidst livsstil med mindre skærmtid.<\/p><p>Ved at tilbyde et håndplukket sortiment af enheder, der fremmer tilstedeværelse og direkte interaktion, håber jeg at kunne inspirere flere til at genoverveje deres digitale vaner. Dette er ikke blot en chance for at reducere daglig stress, men også en mulighed for at genopdage glæden ved de simple ting i livet uden konstante notifikationer.<\/p><p>Ved at tilgængeliggøre disse værktøjer bredt, ønsker jeg at opmuntre til en bølge af forandring, hvor flere oplever de personlige og sociale fordele, som følger med et liv mindre domineret af smartphonens krav.<\/p>",
            "text_style": "body"
          }
        },
        "button_rVz8mX": {
          "type": "button",
          "settings": {
            "button_label": "",
            "button_link": "",
            "button_style_secondary": false
          }
        }
      },
      "block_order": ["heading_4NpeXJ", "text_9hfWtU", "button_rVz8mX"],
      "settings": {
        "image": "shopify:\/\/shop_images\/shoplogo.png",
        "height": "adapt",
        "desktop_image_width": "medium",
        "layout": "image_first",
        "image_behavior": "none",
        "content_layout": "no-overlap",
        "desktop_content_position": "top",
        "desktop_content_alignment": "left",
        "mobile_content_alignment": "left",
        "section_color_scheme": "",
        "color_scheme": "",
        "padding_top": 36,
        "padding_bottom": 36
      }
    },
    "main": {
      "type": "main-page",
      "settings": { "padding_top": 28, "padding_bottom": 48 }
    }
  },
  "order": [
    "rich_text_DWUf4Y",
    "image_with_text_tU3CRX",
    "image_with_text_xQcGLD",
    "image_banner_V9TRwP",
    "image_with_text_M9M7XT",
    "main"
  ]
}
